nikki099_de_toolkit/__init__.py
nikki099_de_toolkit/main.py
nikki099_de_toolkit/vm.py
nikki099_de_toolkit-0.1.0.dist-info/METADATA
nikki099_de_toolkit-0.1.0.dist-info/WHEEL
nikki099_de_toolkit-0.1.0.dist-info/entry_points.txt
nikki099_de_toolkit-0.1.0.dist-info/RECORD
