Metadata-Version: 2.3
Name: nikki099-de-toolkit
Version: 0.1.0
Summary: 
Author: nikki xie
Author-email: nikki099@gmail.com
Requires-Python: >=3.12,<4.0
Classifier: Programming Language :: Python :: 3
Classifier: Programming Language :: Python :: 3.12
Classifier: Programming Language :: Python :: 3.13
Requires-Dist: click (>=8.1.8,<9.0.0)
